wisconsinsc_cleaner/mappings.txt
wisconsinsc_cleaner/wsc_clean.py
wisconsinsc_cleaner-0.0.3.dist-info/LICENSE
wisconsinsc_cleaner-0.0.3.dist-info/METADATA
wisconsinsc_cleaner-0.0.3.dist-info/WHEEL
wisconsinsc_cleaner-0.0.3.dist-info/entry_points.txt
wisconsinsc_cleaner-0.0.3.dist-info/top_level.txt
wisconsinsc_cleaner-0.0.3.dist-info/RECORD
