Metadata-Version: 2.1
Name: wisconsinsc_cleaner
Version: 0.0.3
Summary: A tool to clean and uniform annotation files from Wisconsin Sleep Cohort (WSC), distributed by NSRR
Project-URL: Homepage, https://codeberg.org/LucaCerina/WisconsinSC_cleaner
Project-URL: Bug Tracker, https://codeberg.org/LucaCerina/WisconsinSC_cleaner/issues
Keywords: data storage,data cleaning,medical records
Classifier: Programming Language :: Python :: 3
Classifier: License :: OSI Approved :: MIT License
Classifier: Operating System :: OS Independent
Classifier: Development Status :: 4 - Beta
Requires-Python: >=3.8
License-File: LICENSE
